asgi_client/__init__.py
asgi_client/py.typed
asgi_client/tests/__init__.py
asgi_client/tests/conftest.py
asgi_client/tests/test_testclient.py
asgi_client-0.0.11.dist-info/METADATA
asgi_client-0.0.11.dist-info/WHEEL
asgi_client-0.0.11.dist-info/RECORD
